sdss_brain/__init__.py
sdss_brain/config.py
sdss_brain/core.py
sdss_brain/exceptions.py
sdss_brain/api/__init__.py
sdss_brain/api/client.py
sdss_brain/api/handler.py
sdss_brain/api/io.py
sdss_brain/api/manager.py
sdss_brain/auth/__init__.py
sdss_brain/auth/htpass.py
sdss_brain/auth/netrc.py
sdss_brain/auth/user.py
sdss_brain/datamodel/__init__.py
sdss_brain/datamodel/products.py
sdss_brain/datamodel/versions.py
sdss_brain/etc/api_profiles.yml
sdss_brain/etc/sdss_brain.yml
sdss_brain/helpers/__init__.py
sdss_brain/helpers/database.py
sdss_brain/helpers/decorators.py
sdss_brain/helpers/io.py
sdss_brain/helpers/parsing.py
sdss_brain/mixins/__init__.py
sdss_brain/mixins/access.py
sdss_brain/mixins/datamodel.py
sdss_brain/mixins/mma.py
sdss_brain/tools/__init__.py
sdss_brain/tools/cubes.py
sdss_brain/tools/spectra.py
sdss_brain-0.4.0.data/scripts/sdss_brain
sdss_brain-0.4.0.dist-info/LICENSE.md
sdss_brain-0.4.0.dist-info/METADATA
sdss_brain-0.4.0.dist-info/WHEEL
sdss_brain-0.4.0.dist-info/top_level.txt
sdss_brain-0.4.0.dist-info/RECORD
