Metadata-Version: 2.1
Name: sdss-brain
Version: 0.4.0
Summary: Core Brain for SDSS
Home-page: https://github.com/sdss/sdss_brain
Author: Brian Cherinka
Author-email: bcherinka@stsci.edu
License: BSD 3-Clause License
Project-URL: Repository, https://github.com/sdss/sdss_brain
Project-URL: Documentation, https://sdss-brain.readthedocs.org
Keywords: astronomy,software
Platform: UNKNOWN
Classifier: Intended Audience :: Science/Research
Classifier: Natural Language :: English
Classifier: Operating System :: OS Independent
Classifier: Programming Language :: Python
Classifier: Programming Language :: Python :: 3.8
Classifier: Programming Language :: Python :: 3.9
Classifier: Programming Language :: Python :: 3.10
Classifier: Topic :: Documentation :: Sphinx
Classifier: Topic :: Software Development :: Libraries :: Python Modules
Requires-Python: >=3.8
Requires-Dist: sdss-tree (>=3.1)
Requires-Dist: sdss-access (>=2.0)
Requires-Dist: sdssdb (>=0.5)
Requires-Dist: sdsstools (>=0.4.0)
Requires-Dist: astropy (>=3.3)
Requires-Dist: specutils (>=1.8)
Requires-Dist: httpx (>=0.21.0)
Requires-Dist: pydantic (>=1.10.0)
Requires-Dist: datamodel-code-generator (>=0.13.1)
Provides-Extra: dev
Requires-Dist: Sphinx (>=5.0.0) ; extra == 'dev'
Requires-Dist: furo (>=2021.6.18b36) ; extra == 'dev'
Requires-Dist: sphinx-copybutton (>=0.3.3) ; extra == 'dev'
Requires-Dist: sphinx-inline-tabs (>=2021.3.28b7) ; extra == 'dev'
Requires-Dist: ipython (>=7.9.0) ; extra == 'dev'
Requires-Dist: matplotlib (>=3.1.1) ; extra == 'dev'
Requires-Dist: flake8 (>=3.7.9) ; extra == 'dev'
Requires-Dist: doc8 (>=0.8.0) ; extra == 'dev'
Requires-Dist: pytest (>=5.2.2) ; extra == 'dev'
Requires-Dist: pytest-asyncio (>=0.10.0) ; extra == 'dev'
Requires-Dist: pytest-cov (>=2.8.1) ; extra == 'dev'
Requires-Dist: pytest-mock (>=3.7) ; extra == 'dev'
Requires-Dist: pytest-sugar (>=0.9.2) ; extra == 'dev'
Requires-Dist: pytest-remotedata (>=0.3.2) ; extra == 'dev'
Requires-Dist: respx (>=0.19) ; extra == 'dev'
Requires-Dist: passlib (>=1.7.1) ; extra == 'dev'
Requires-Dist: isort (>=4.3.21) ; extra == 'dev'
Requires-Dist: codecov (>=2.0.15) ; extra == 'dev'
Requires-Dist: coverage[toml] (>=5.0) ; extra == 'dev'
Requires-Dist: ipdb (>=0.12.3) ; extra == 'dev'
Requires-Dist: sdsstools[dev] (>=0.4.0) ; extra == 'dev'
Requires-Dist: sqlalchemy (>=1.3.13) ; extra == 'dev'
Requires-Dist: invoke (>=1.3.0) ; extra == 'dev'
Requires-Dist: twine (>=3.1.1) ; extra == 'dev'
Requires-Dist: wheel (>=0.33.6) ; extra == 'dev'
Provides-Extra: docs
Requires-Dist: Sphinx (>=5.0.0) ; extra == 'docs'
Requires-Dist: furo (>=2021.6.18b36) ; extra == 'docs'
Requires-Dist: sphinx-copybutton (>=0.3.3) ; extra == 'docs'
Requires-Dist: sphinx-inline-tabs (>=2021.3.28b7) ; extra == 'docs'
Provides-Extra: extras
Requires-Dist: matplotlib (>=3.1.1) ; extra == 'extras'
Requires-Dist: tqdm (>=4.46.0) ; extra == 'extras'
Requires-Dist: passlib (>=1.7.1) ; extra == 'extras'
Requires-Dist: tabulate (>=0.8.7) ; extra == 'extras'
